doc_analyzer/__init__.py
doc_analyzer/documents/__init__.py
doc_analyzer/documents/base.py
doc_analyzer/documents/html.py
doc_analyzer/documents/pdf.py
doc_analyzer/documents/transcript.py
doc_analyzer/processors/__init__.py
doc_analyzer/processors/aws_textract.py
doc_analyzer/processors/base.py
doc_analyzer/processors/html.py
doc_analyzer/processors/textract.py
doc_analyzer/processors/whisper.py
doc_analyzer/utils/__init__.py
doc_analyzer/utils/audio.py
doc_analyzer/utils/html.py
doc_analyzer/utils/pdf.py
doc_analyzer/utils/textract.py
doc_analyzer/utils/transcribe.py
doc_analyzer-0.1.6.dist-info/METADATA
doc_analyzer-0.1.6.dist-info/WHEEL
doc_analyzer-0.1.6.dist-info/top_level.txt
doc_analyzer-0.1.6.dist-info/RECORD
