Metadata-Version: 2.1
Name: doc-analyzer
Version: 0.1.6
Author: Peter Darche
Requires-Dist: PyMuPDF
Requires-Dist: PyPDF2
Requires-Dist: requests
Requires-Dist: langchain
Requires-Dist: llama-index
Requires-Dist: boto3
Requires-Dist: scikit-learn
Requires-Dist: openai
Requires-Dist: pydantic
Requires-Dist: pydub
Requires-Dist: pandas
Requires-Dist: textract
Requires-Dist: html2text
Requires-Dist: beautifulsoup4
